<?xml version="1.0" encoding="UTF-8"?>
<entry xmlns="http://www.w3.org/2005/Atom" xmlns:dcterms="http://purl.org/dc/terms" xmlns:xhtml="http://www.w3.org/1999/xhtml">
  <title>Steelheart</title>
  <id>urn:book:710c0b84-d2a1-4e5e-b8ef-05e615270c66</id>
  <updated>2016-07-17T05:53:07Z</updated>
  <link href="./book_38.xml" type="application/atom+xml;type=entry;profile=opds-catalog" rel="self" title="Steelheart" />
  <link href="../index.xml" type="application/atom+xml;profile=opds-catalog;kind=navigation" rel="start" title="Jack's Library" />
  <link href="../index.xml" type="application/atom+xml;profile=opds-catalog;kind=navigation" rel="breadcrumb" title="Jack's Library" />
  <link href="../authorlist/authorlist_Page_1.xml" type="application/atom+xml;profile=opds-catalog;kind=navigation" rel="breadcrumb" title="Authors" />
  <link href="../authorlist/authorlist_S_Page_1.xml" type="application/atom+xml;profile=opds-catalog;kind=navigation" rel="breadcrumb" title="Authors starting with S" />
  <link href="../../Brandon%20Sanderson/Steelheart%20%2838%29/c2o_resizedcover.jpg" type="image/jpg" rel="http://opds-spec.org/image" />
  <link href="../../Brandon%20Sanderson/Steelheart%20%2838%29/c2o_thumbnail.jpg" type="image/jpg" rel="http://opds-spec.org/image/thumbnail" />
  <link href="../../Brandon%20Sanderson/Steelheart%20%2838%29/Steelheart%20-%20Brandon%20Sanderson.azw3" type="application/octet-stream" rel="http://opds-spec.org/acquisition" title="Download this ebook as AZW3" displaysize="904 KB" />
  <author>
    <name>Brandon Sanderson</name>
    <uri>../author_0/author_32_Page_1.xml</uri>
  </author>
  <published>2014-05-28T10:00:00Z</published>
  <dcterms:language>it</dcterms:language>
  <dcterms:publisher>Fanucci Editore</dcterms:publisher>
  <category term="Epic" />
  <category term="Fantasy" />
  <category term="Fiction" />
  <category term="Lang:it" />
  <content type="text/html">
    <p>
      <strong>Rating:</strong>
      Not rated
    </p>
    <p>
      <strong>Tags:</strong>
      Epic, Fantasy, Fiction, Lang:it
    </p>
    <p>
      <strong>Summary</strong>
    </p>
    <div xmlns="">
      <p class="description">
        David è solo un bambino quando
      l’oscurità
        <br />
        perpetua cala sulla Terra e in cielo compare Calamity,
      una misteriosa stella
        <br />
        che dona a uomini e donne, prima di allora intrappolati
      nelle loro ordinarie
        <br />
        esistenze, poteri fuori dal comune. Questi esseri
      straordinari vengono
        <br />
        ribattezzati con il nome di Epici e ben presto il loro
      dono li rende avidi di
        <br />
        supremazia sugli altri uomini. Due anni più tardi,
      a Newcago, la città che una
        <br />
        volta era stata Chicago, David assiste
      all’assassinio di suo padre da parte di
        <br />
        uno degli Epici più potenti, Steelheart. Ora cerca
      vendetta, e sa che l’unico
        <br />
        modo per ottenerla è entrare a far parte degli
      Eliminatori, un’organizzazione
        <br />
        che agisce nell’ombra, studiando le debolezze
      degli Epici e combattendoli
        <br />
        strenuamente. E nonostante tutti pensino che
      Steelheart, Cuore d’Acciaio, sia
        <br />
        invincibile, David sa che non è così,
      perché lo ha visto sanguinare con i propri
        <br />
        occhi.
      </p>
      <br class="description" />
      <br />
      <br class="description" />
      <br />
      <br class="description" />
      <br />
      <br class="description" />
      <br />
      <br class="description" />
      <br />
      <br class="description" />
      <br />
      <br class="description" />
      <br />
      <br class="description" />
      <br />
      <p class="description">
        <br />
         
      </p>
      <p class="description">
        Un fantasy in cui ad avere i
      superpoteri sono
        <br />
        i cattivi, in stile Marvel, un romanzo che vi
      lascerà senza fiato.
      </p>
    </div>
  </content>
  <link href="../author_0/author_32_Page_1.xml" type="application/atom+xml;profile=opds-catalog;kind=navigation" rel="related" title="Books by Brandon Sanderson" />
  <link href="http://www.goodreads.com/book/title/Steelheart" type="text/html" rel="related" title="This book on Goodreads" />
  <link href="http://en.wikipedia.org/wiki/Steelheart" type="text/html" rel="related" title="This book on Wikipedia" />
  <link href="http://www.librarything.com/title/Steelheart%20Brandon%20Sanderson" type="text/html" rel="related" title="This book on LibraryThing" />
  <link href="http://www.amazon.com/gp/search/ref=sr_adv_b/?search-alias=stripbooks&amp;unfiltered=1&amp;sort=relevanceexprank&amp;field-title=Steelheart&amp;field-author=Brandon%20Sanderson" type="text/html" rel="related" title="This book on Amazon" />
  <link href="http://www.goodreads.com/book/author/Brandon%20Sanderson" type="text/html" rel="related" title="Brandon Sanderson on Goodreads" />
  <link href="http://en.wikipedia.org/wiki/Brandon%20Sanderson" type="text/html" rel="related" title="Brandon Sanderson on Wikipedia" />
  <link href="http://www.librarything.com/author/SandersonBrandon" type="text/html" rel="related" title="Brandon Sanderson on LibraryThing" />
  <link href="http://www.amazon.com/gp/search/ref=sr_adv_b/?search-alias=stripbooks&amp;unfiltered=1&amp;sort=relevanceexprank&amp;field-author=Brandon%20Sanderson" type="text/html" rel="related" title="Brandon Sanderson on Amazon" />
  <link href="http://www.isfdb.org/cgi-bin/ea.cgi?Brandon%20Sanderson" type="text/html" rel="related" title="Brandon Sanderson on ISFDB" />
</entry>
