<?xml version="1.0" encoding="UTF-8"?>
<entry xmlns="http://www.w3.org/2005/Atom" xmlns:dcterms="http://purl.org/dc/terms" xmlns:xhtml="http://www.w3.org/1999/xhtml">
  <title>Mortdecai e il complotto del secolo</title>
  <id>urn:book:6f2b400a-e1ab-4985-bf98-4efb4d3dfbd6</id>
  <updated>2016-07-17T05:53:26Z</updated>
  <link href="./book_98.xml" type="application/atom+xml;type=entry;profile=opds-catalog" rel="self" title="Mortdecai e il complotto del secolo" />
  <link href="../index.xml" type="application/atom+xml;profile=opds-catalog;kind=navigation" rel="start" title="Jack's Library" />
  <link href="../index.xml" type="application/atom+xml;profile=opds-catalog;kind=navigation" rel="breadcrumb" title="Jack's Library" />
  <link href="../authorlist/authorlist_Page_1.xml" type="application/atom+xml;profile=opds-catalog;kind=navigation" rel="breadcrumb" title="Authors" />
  <link href="../authorlist/authorlist_B_Page_1.xml" type="application/atom+xml;profile=opds-catalog;kind=navigation" rel="breadcrumb" title="Authors starting with B" />
  <link href="../../Kyril%20Bonfiglioli/Mortdecai%20e%20il%20complotto%20del%20secolo%20%2898%29/c2o_resizedcover.jpg" type="image/jpg" rel="http://opds-spec.org/image" />
  <link href="../../Kyril%20Bonfiglioli/Mortdecai%20e%20il%20complotto%20del%20secolo%20%2898%29/c2o_thumbnail.jpg" type="image/jpg" rel="http://opds-spec.org/image/thumbnail" />
  <link href="../../Kyril%20Bonfiglioli/Mortdecai%20e%20il%20complotto%20del%20secolo%20%2898%29/Mortdecai%20e%20il%20complotto%20del%20se%20-%20Kyril%20Bonfiglioli.azw3" type="application/octet-stream" rel="http://opds-spec.org/acquisition" title="Download this ebook as AZW3" displaysize="394 KB" />
  <author>
    <name>Kyril Bonfiglioli</name>
    <uri>../author_0/author_79_Page_1.xml</uri>
  </author>
  <published>2015-05-11T10:00:00Z</published>
  <dcterms:language>it</dcterms:language>
  <dcterms:publisher>EDIZIONI PIEMME</dcterms:publisher>
  <category term="Lang:it" />
  <content type="text/html">
    <p>
      <strong>Rating:</strong>
      Not rated
    </p>
    <p>
      <strong>Tags:</strong>
      Lang:it
    </p>
  </content>
  <link href="../author_0/author_79_Page_1.xml" type="application/atom+xml;profile=opds-catalog;kind=navigation" rel="related" title="Books by Kyril Bonfiglioli" />
  <link href="http://www.goodreads.com/book/title/Mortdecai%20e%20il%20complotto%20del%20secolo" type="text/html" rel="related" title="This book on Goodreads" />
  <link href="http://en.wikipedia.org/wiki/Mortdecai%20e%20il%20complotto%20del%20secolo" type="text/html" rel="related" title="This book on Wikipedia" />
  <link href="http://www.librarything.com/title/Mortdecai%20e%20il%20complotto%20del%20secolo%20Kyril%20Bonfiglioli" type="text/html" rel="related" title="This book on LibraryThing" />
  <link href="http://www.amazon.com/gp/search/ref=sr_adv_b/?search-alias=stripbooks&amp;unfiltered=1&amp;sort=relevanceexprank&amp;field-title=Mortdecai%20e%20il%20complotto%20del%20secolo&amp;field-author=Kyril%20Bonfiglioli" type="text/html" rel="related" title="This book on Amazon" />
  <link href="http://www.goodreads.com/book/author/Kyril%20Bonfiglioli" type="text/html" rel="related" title="Kyril Bonfiglioli on Goodreads" />
  <link href="http://en.wikipedia.org/wiki/Kyril%20Bonfiglioli" type="text/html" rel="related" title="Kyril Bonfiglioli on Wikipedia" />
  <link href="http://www.librarything.com/author/BonfiglioliKyril" type="text/html" rel="related" title="Kyril Bonfiglioli on LibraryThing" />
  <link href="http://www.amazon.com/gp/search/ref=sr_adv_b/?search-alias=stripbooks&amp;unfiltered=1&amp;sort=relevanceexprank&amp;field-author=Kyril%20Bonfiglioli" type="text/html" rel="related" title="Kyril Bonfiglioli on Amazon" />
  <link href="http://www.isfdb.org/cgi-bin/ea.cgi?Kyril%20Bonfiglioli" type="text/html" rel="related" title="Kyril Bonfiglioli on ISFDB" />
</entry>
